simplevectors/SimpleVector.py
simplevectors/__init__.py
simplevectors/add_vectors.py
SimpleVectors-0.0.5.dist-info/METADATA
SimpleVectors-0.0.5.dist-info/WHEEL
SimpleVectors-0.0.5.dist-info/top_level.txt
SimpleVectors-0.0.5.dist-info/RECORD
